[
  {
    "text": "안녕. 좋은 목소리를 내기 위해 많이 노력했어. 잘 부탁해"
  },
  {
    "text": "안녕하세요. 좋은 목소리를 내기 위해 많이 노력했어요. 잘 부탁해요."
  },
  {
    "text": "아..아 걱정마세요. 바로 처리해드릴게요!"
  },
  {
    "text": "안녕하세요. 선생님. 제 목소리는 어떤가요?"
  },
  {
    "text": "훈육 지원부 매화원의 코코나입니다. 이래도 어엿한 교관이라구요."
  },
  {
    "text": "블루 아카이브"
  },
  {
    "text": "어서오세요. 선생님"
  },
  {
    "text": "어서오세요. 주인님. 메이드 아리스에게 모든지 맡겨주세요."
  },
  {
    "text": "많은 관심을 주셔서 감사합니다."
  },
  {
    "text": "선생님이 많은 것을 가르쳐주셔서, 정말 행복해요. 앞으로도 열심히 할게요!"
  }
]